<?xml version="1.0" encoding="utf-8"?>
<abapGit version="v1.0.0" serializer="LCL_OBJECT_WEBI" serializer_version="v1.0.0">
 <asx:abap xmlns:asx="http://www.sap.com/abapxml" version="1.0">
  <asx:values>
   <WEBI>
    <VEPTEXT>Webservice - Perfil do Colaborador</VEPTEXT>
    <PVEPHEADER>
     <VEPHEADER>
      <VEPNAME>ZAH_PERFIL_COLABORADOR</VEPNAME>
      <VERSION>A</VERSION>
      <VEPNAMEEXT>ZAH_Perfil_colaborador</VEPNAMEEXT>
      <DEFAULT_MAPPING>X</DEFAULT_MAPPING>
     </VEPHEADER>
    </PVEPHEADER>
    <PVEPFUNCTION>
     <VEPFUNCTION>
      <VEPNAME>ZAH_PERFIL_COLABORADOR</VEPNAME>
      <VERSION>A</VERSION>
      <FUNCTION>ZAH_USER_PROFILE</FUNCTION>
      <MAPPEDNAME>ZahUserProfile</MAPPEDNAME>
      <IS_EXPOSED>X</IS_EXPOSED>
     </VEPFUNCTION>
    </PVEPFUNCTION>
    <PVEPPARAMETER>
     <VEPPARAMETER>
      <VEPNAME>ZAH_PERFIL_COLABORADOR</VEPNAME>
      <VERSION>A</VERSION>
      <FUNCTION>ZAH_USER_PROFILE</FUNCTION>
      <VEPPARAM>EXP_USER_PROFILES</VEPPARAM>
      <VEPPARAMTYPE>O</VEPPARAMTYPE>
      <MAPPEDNAME>ExpUserProfiles</MAPPEDNAME>
      <IS_EXPOSED>X</IS_EXPOSED>
      <IS_INITIAL>X</IS_INITIAL>
      <TYPENAME>ZahTtUserProfile</TYPENAME>
     </VEPPARAMETER>
     <VEPPARAMETER>
      <VEPNAME>ZAH_PERFIL_COLABORADOR</VEPNAME>
      <VERSION>A</VERSION>
      <FUNCTION>ZAH_USER_PROFILE</FUNCTION>
      <VEPPARAM>IT_NUM_COL</VEPPARAM>
      <VEPPARAMTYPE>I</VEPPARAMTYPE>
      <MAPPEDNAME>ItNumCol</MAPPEDNAME>
      <IS_EXPOSED>X</IS_EXPOSED>
      <IS_INITIAL>X</IS_INITIAL>
      <TYPENAME>ZahTtNumEmp</TYPENAME>
     </VEPPARAMETER>
    </PVEPPARAMETER>
    <PVEPTYPE>
     <VEPTYPE>
      <VEPNAME>ZAH_PERFIL_COLABORADOR</VEPNAME>
      <VERSION>A</VERSION>
      <TYPENAME>BANKA</TYPENAME>
      <TYPE>E</TYPE>
     </VEPTYPE>
     <VEPTYPE>
      <VEPNAME>ZAH_PERFIL_COLABORADOR</VEPNAME>
      <VERSION>A</VERSION>
      <TYPENAME>BANKN</TYPENAME>
      <TYPE>E</TYPE>
     </VEPTYPE>
     <VEPTYPE>
      <VEPNAME>ZAH_PERFIL_COLABORADOR</VEPNAME>
      <VERSION>A</VERSION>
      <TYPENAME>CHAR5</TYPENAME>
      <TYPE>E</TYPE>
     </VEPTYPE>
     <VEPTYPE>
      <VEPNAME>ZAH_PERFIL_COLABORADOR</VEPNAME>
      <VERSION>A</VERSION>
      <TYPENAME>CHAR75</TYPENAME>
      <TYPE>E</TYPE>
     </VEPTYPE>
     <VEPTYPE>
      <VEPNAME>ZAH_PERFIL_COLABORADOR</VEPNAME>
      <VERSION>A</VERSION>
      <TYPENAME>CHAR8</TYPENAME>
      <TYPE>E</TYPE>
     </VEPTYPE>
     <VEPTYPE>
      <VEPNAME>ZAH_PERFIL_COLABORADOR</VEPNAME>
      <VERSION>A</VERSION>
      <TYPENAME>COMM_ID_LONG</TYPENAME>
      <TYPE>E</TYPE>
     </VEPTYPE>
     <VEPTYPE>
      <VEPNAME>ZAH_PERFIL_COLABORADOR</VEPNAME>
      <VERSION>A</VERSION>
      <TYPENAME>CTTXT</TYPENAME>
      <TYPE>E</TYPE>
     </VEPTYPE>
     <VEPTYPE>
      <VEPNAME>ZAH_PERFIL_COLABORADOR</VEPNAME>
      <VERSION>A</VERSION>
      <TYPENAME>DATUM</TYPENAME>
      <TYPE>E</TYPE>
     </VEPTYPE>
     <VEPTYPE>
      <VEPNAME>ZAH_PERFIL_COLABORADOR</VEPNAME>
      <VERSION>A</VERSION>
      <TYPENAME>EMFTX</TYPENAME>
      <TYPE>E</TYPE>
     </VEPTYPE>
     <VEPTYPE>
      <VEPNAME>ZAH_PERFIL_COLABORADOR</VEPNAME>
      <VERSION>A</VERSION>
      <TYPENAME>FATXT</TYPENAME>
      <TYPE>E</TYPE>
     </VEPTYPE>
     <VEPTYPE>
      <VEPNAME>ZAH_PERFIL_COLABORADOR</VEPNAME>
      <VERSION>A</VERSION>
      <TYPENAME>GBDAT</TYPENAME>
      <TYPE>E</TYPE>
     </VEPTYPE>
     <VEPTYPE>
      <VEPNAME>ZAH_PERFIL_COLABORADOR</VEPNAME>
      <VERSION>A</VERSION>
      <TYPENAME>GESCH</TYPENAME>
      <TYPE>E</TYPE>
     </VEPTYPE>
     <VEPTYPE>
      <VEPNAME>ZAH_PERFIL_COLABORADOR</VEPNAME>
      <VERSION>A</VERSION>
      <TYPENAME>IBAN</TYPENAME>
      <TYPE>E</TYPE>
     </VEPTYPE>
     <VEPTYPE>
      <VEPNAME>ZAH_PERFIL_COLABORADOR</VEPNAME>
      <VERSION>A</VERSION>
      <TYPENAME>ICNUM</TYPENAME>
      <TYPE>E</TYPE>
     </VEPTYPE>
     <VEPTYPE>
      <VEPNAME>ZAH_PERFIL_COLABORADOR</VEPNAME>
      <VERSION>A</VERSION>
      <TYPENAME>NATIO</TYPENAME>
      <TYPE>E</TYPE>
     </VEPTYPE>
     <VEPTYPE>
      <VEPNAME>ZAH_PERFIL_COLABORADOR</VEPNAME>
      <VERSION>A</VERSION>
      <TYPENAME>NUM9</TYPENAME>
      <TYPE>E</TYPE>
     </VEPTYPE>
     <VEPTYPE>
      <VEPNAME>ZAH_PERFIL_COLABORADOR</VEPNAME>
      <VERSION>A</VERSION>
      <TYPENAME>ORGEH</TYPENAME>
      <TYPE>E</TYPE>
     </VEPTYPE>
     <VEPTYPE>
      <VEPNAME>ZAH_PERFIL_COLABORADOR</VEPNAME>
      <VERSION>A</VERSION>
      <TYPENAME>PAD_CNAME</TYPENAME>
      <TYPE>E</TYPE>
     </VEPTYPE>
     <VEPTYPE>
      <VEPNAME>ZAH_PERFIL_COLABORADOR</VEPNAME>
      <VERSION>A</VERSION>
      <TYPENAME>PAD_NACHN</TYPENAME>
      <TYPE>E</TYPE>
     </VEPTYPE>
     <VEPTYPE>
      <VEPNAME>ZAH_PERFIL_COLABORADOR</VEPNAME>
      <VERSION>A</VERSION>
      <TYPENAME>PAD_ORT01</TYPENAME>
      <TYPE>E</TYPE>
     </VEPTYPE>
     <VEPTYPE>
      <VEPNAME>ZAH_PERFIL_COLABORADOR</VEPNAME>
      <VERSION>A</VERSION>
      <TYPENAME>PAD_VORNA</TYPENAME>
      <TYPE>E</TYPE>
     </VEPTYPE>
     <VEPTYPE>
      <VEPNAME>ZAH_PERFIL_COLABORADOR</VEPNAME>
      <VERSION>A</VERSION>
      <TYPENAME>PERNR_D</TYPENAME>
      <TYPE>E</TYPE>
     </VEPTYPE>
     <VEPTYPE>
      <VEPNAME>ZAH_PERFIL_COLABORADOR</VEPNAME>
      <VERSION>A</VERSION>
      <TYPENAME>PERSNO</TYPENAME>
      <TYPE>E</TYPE>
     </VEPTYPE>
     <VEPTYPE>
      <VEPNAME>ZAH_PERFIL_COLABORADOR</VEPNAME>
      <VERSION>A</VERSION>
      <TYPENAME>PLSTX</TYPENAME>
      <TYPE>E</TYPE>
     </VEPTYPE>
     <VEPTYPE>
      <VEPNAME>ZAH_PERFIL_COLABORADOR</VEPNAME>
      <VERSION>A</VERSION>
      <TYPENAME>PSG_IDNUM</TYPENAME>
      <TYPE>E</TYPE>
     </VEPTYPE>
     <VEPTYPE>
      <VEPNAME>ZAH_PERFIL_COLABORADOR</VEPNAME>
      <VERSION>A</VERSION>
      <TYPENAME>PSTLZ_HR</TYPENAME>
      <TYPE>E</TYPE>
     </VEPTYPE>
     <VEPTYPE>
      <VEPNAME>ZAH_PERFIL_COLABORADOR</VEPNAME>
      <VERSION>A</VERSION>
      <TYPENAME>STLTX</TYPENAME>
      <TYPE>E</TYPE>
     </VEPTYPE>
     <VEPTYPE>
      <VEPNAME>ZAH_PERFIL_COLABORADOR</VEPNAME>
      <VERSION>A</VERSION>
      <TYPENAME>ZAH_S_NUM_EMP</TYPENAME>
      <TYPE>S</TYPE>
     </VEPTYPE>
     <VEPTYPE>
      <VEPNAME>ZAH_PERFIL_COLABORADOR</VEPNAME>
      <VERSION>A</VERSION>
      <TYPENAME>ZAH_S_USER_PROFILE</TYPENAME>
      <TYPE>S</TYPE>
     </VEPTYPE>
     <VEPTYPE>
      <VEPNAME>ZAH_PERFIL_COLABORADOR</VEPNAME>
      <VERSION>A</VERSION>
      <TYPENAME>ZAH_TT_NUM_EMP</TYPENAME>
      <TYPE>T</TYPE>
     </VEPTYPE>
     <VEPTYPE>
      <VEPNAME>ZAH_PERFIL_COLABORADOR</VEPNAME>
      <VERSION>A</VERSION>
      <TYPENAME>ZAH_TT_USER_PROFILE</TYPENAME>
      <TYPE>T</TYPE>
     </VEPTYPE>
     <VEPTYPE>
      <VEPNAME>ZAH_PERFIL_COLABORADOR</VEPNAME>
      <VERSION>A</VERSION>
      <TYPENAME>ZAMTHRTELE</TYPENAME>
      <TYPE>E</TYPE>
     </VEPTYPE>
     <VEPTYPE>
      <VEPNAME>ZAH_PERFIL_COLABORADOR</VEPNAME>
      <VERSION>A</VERSION>
      <TYPENAME>ZahSNumEmp</TYPENAME>
      <ORGINAL>ZAH_S_NUM_EMP</ORGINAL>
      <TYPE>S</TYPE>
     </VEPTYPE>
     <VEPTYPE>
      <VEPNAME>ZAH_PERFIL_COLABORADOR</VEPNAME>
      <VERSION>A</VERSION>
      <TYPENAME>ZahSUserProfile</TYPENAME>
      <ORGINAL>ZAH_S_USER_PROFILE</ORGINAL>
      <TYPE>S</TYPE>
     </VEPTYPE>
     <VEPTYPE>
      <VEPNAME>ZAH_PERFIL_COLABORADOR</VEPNAME>
      <VERSION>A</VERSION>
      <TYPENAME>ZahTtNumEmp</TYPENAME>
      <ORGINAL>ZAH_TT_NUM_EMP</ORGINAL>
      <TYPE>T</TYPE>
     </VEPTYPE>
     <VEPTYPE>
      <VEPNAME>ZAH_PERFIL_COLABORADOR</VEPNAME>
      <VERSION>A</VERSION>
      <TYPENAME>ZahTtUserProfile</TYPENAME>
      <ORGINAL>ZAH_TT_USER_PROFILE</ORGINAL>
      <TYPE>T</TYPE>
     </VEPTYPE>
    </PVEPTYPE>
    <PVEPELEMTYPE>
     <VEPELEMTYPE>
      <VEPNAME>ZAH_PERFIL_COLABORADOR</VEPNAME>
      <VERSION>A</VERSION>
      <TYPENAME>BANKA</TYPENAME>
      <KIND>DTEL</KIND>
      <BUILD_IN_TYPE>CHAR</BUILD_IN_TYPE>
      <LENGTH>60</LENGTH>
      <ABAPTYPE>C</ABAPTYPE>
     </VEPELEMTYPE>
     <VEPELEMTYPE>
      <VEPNAME>ZAH_PERFIL_COLABORADOR</VEPNAME>
      <VERSION>A</VERSION>
      <TYPENAME>BANKN</TYPENAME>
      <KIND>DTEL</KIND>
      <BUILD_IN_TYPE>CHAR</BUILD_IN_TYPE>
      <LENGTH>18</LENGTH>
      <ABAPTYPE>C</ABAPTYPE>
     </VEPELEMTYPE>
     <VEPELEMTYPE>
      <VEPNAME>ZAH_PERFIL_COLABORADOR</VEPNAME>
      <VERSION>A</VERSION>
      <TYPENAME>CHAR5</TYPENAME>
      <KIND>DTEL</KIND>
      <BUILD_IN_TYPE>CHAR</BUILD_IN_TYPE>
      <LENGTH>5</LENGTH>
      <ABAPTYPE>C</ABAPTYPE>
     </VEPELEMTYPE>
     <VEPELEMTYPE>
      <VEPNAME>ZAH_PERFIL_COLABORADOR</VEPNAME>
      <VERSION>A</VERSION>
      <TYPENAME>CHAR75</TYPENAME>
      <KIND>DTEL</KIND>
      <BUILD_IN_TYPE>CHAR</BUILD_IN_TYPE>
      <LENGTH>75</LENGTH>
      <ABAPTYPE>C</ABAPTYPE>
     </VEPELEMTYPE>
     <VEPELEMTYPE>
      <VEPNAME>ZAH_PERFIL_COLABORADOR</VEPNAME>
      <VERSION>A</VERSION>
      <TYPENAME>CHAR8</TYPENAME>
      <KIND>DTEL</KIND>
      <BUILD_IN_TYPE>CHAR</BUILD_IN_TYPE>
      <LENGTH>8</LENGTH>
      <ABAPTYPE>C</ABAPTYPE>
     </VEPELEMTYPE>
     <VEPELEMTYPE>
      <VEPNAME>ZAH_PERFIL_COLABORADOR</VEPNAME>
      <VERSION>A</VERSION>
      <TYPENAME>COMM_ID_LONG</TYPENAME>
      <KIND>DTEL</KIND>
      <BUILD_IN_TYPE>CHAR</BUILD_IN_TYPE>
      <LENGTH>241</LENGTH>
      <ABAPTYPE>C</ABAPTYPE>
     </VEPELEMTYPE>
     <VEPELEMTYPE>
      <VEPNAME>ZAH_PERFIL_COLABORADOR</VEPNAME>
      <VERSION>A</VERSION>
      <TYPENAME>CTTXT</TYPENAME>
      <KIND>DTEL</KIND>
      <BUILD_IN_TYPE>CHAR</BUILD_IN_TYPE>
      <LENGTH>20</LENGTH>
      <ABAPTYPE>C</ABAPTYPE>
     </VEPELEMTYPE>
     <VEPELEMTYPE>
      <VEPNAME>ZAH_PERFIL_COLABORADOR</VEPNAME>
      <VERSION>A</VERSION>
      <TYPENAME>DATUM</TYPENAME>
      <KIND>DTEL</KIND>
      <BUILD_IN_TYPE>DATS</BUILD_IN_TYPE>
      <LENGTH>8</LENGTH>
      <ABAPTYPE>D</ABAPTYPE>
     </VEPELEMTYPE>
     <VEPELEMTYPE>
      <VEPNAME>ZAH_PERFIL_COLABORADOR</VEPNAME>
      <VERSION>A</VERSION>
      <TYPENAME>EMFTX</TYPENAME>
      <KIND>DTEL</KIND>
      <BUILD_IN_TYPE>CHAR</BUILD_IN_TYPE>
      <LENGTH>40</LENGTH>
      <ABAPTYPE>C</ABAPTYPE>
     </VEPELEMTYPE>
     <VEPELEMTYPE>
      <VEPNAME>ZAH_PERFIL_COLABORADOR</VEPNAME>
      <VERSION>A</VERSION>
      <TYPENAME>FATXT</TYPENAME>
      <KIND>DTEL</KIND>
      <BUILD_IN_TYPE>CHAR</BUILD_IN_TYPE>
      <LENGTH>6</LENGTH>
      <ABAPTYPE>C</ABAPTYPE>
     </VEPELEMTYPE>
     <VEPELEMTYPE>
      <VEPNAME>ZAH_PERFIL_COLABORADOR</VEPNAME>
      <VERSION>A</VERSION>
      <TYPENAME>GBDAT</TYPENAME>
      <KIND>DTEL</KIND>
      <BUILD_IN_TYPE>DATS</BUILD_IN_TYPE>
      <LENGTH>8</LENGTH>
      <ABAPTYPE>D</ABAPTYPE>
     </VEPELEMTYPE>
     <VEPELEMTYPE>
      <VEPNAME>ZAH_PERFIL_COLABORADOR</VEPNAME>
      <VERSION>A</VERSION>
      <TYPENAME>GESCH</TYPENAME>
      <KIND>DTEL</KIND>
      <BUILD_IN_TYPE>CHAR</BUILD_IN_TYPE>
      <LENGTH>1</LENGTH>
      <ABAPTYPE>C</ABAPTYPE>
     </VEPELEMTYPE>
     <VEPELEMTYPE>
      <VEPNAME>ZAH_PERFIL_COLABORADOR</VEPNAME>
      <VERSION>A</VERSION>
      <TYPENAME>IBAN</TYPENAME>
      <KIND>DTEL</KIND>
      <BUILD_IN_TYPE>CHAR</BUILD_IN_TYPE>
      <LENGTH>34</LENGTH>
      <ABAPTYPE>C</ABAPTYPE>
     </VEPELEMTYPE>
     <VEPELEMTYPE>
      <VEPNAME>ZAH_PERFIL_COLABORADOR</VEPNAME>
      <VERSION>A</VERSION>
      <TYPENAME>ICNUM</TYPENAME>
      <KIND>DTEL</KIND>
      <BUILD_IN_TYPE>CHAR</BUILD_IN_TYPE>
      <LENGTH>20</LENGTH>
      <ABAPTYPE>C</ABAPTYPE>
     </VEPELEMTYPE>
     <VEPELEMTYPE>
      <VEPNAME>ZAH_PERFIL_COLABORADOR</VEPNAME>
      <VERSION>A</VERSION>
      <TYPENAME>NATIO</TYPENAME>
      <KIND>DTEL</KIND>
      <BUILD_IN_TYPE>CHAR</BUILD_IN_TYPE>
      <LENGTH>15</LENGTH>
      <ABAPTYPE>C</ABAPTYPE>
     </VEPELEMTYPE>
     <VEPELEMTYPE>
      <VEPNAME>ZAH_PERFIL_COLABORADOR</VEPNAME>
      <VERSION>A</VERSION>
      <TYPENAME>NUM9</TYPENAME>
      <KIND>DTEL</KIND>
      <BUILD_IN_TYPE>NUMC</BUILD_IN_TYPE>
      <LENGTH>9</LENGTH>
      <ABAPTYPE>N</ABAPTYPE>
     </VEPELEMTYPE>
     <VEPELEMTYPE>
      <VEPNAME>ZAH_PERFIL_COLABORADOR</VEPNAME>
      <VERSION>A</VERSION>
      <TYPENAME>ORGEH</TYPENAME>
      <KIND>DTEL</KIND>
      <BUILD_IN_TYPE>NUMC</BUILD_IN_TYPE>
      <LENGTH>8</LENGTH>
      <ABAPTYPE>N</ABAPTYPE>
     </VEPELEMTYPE>
     <VEPELEMTYPE>
      <VEPNAME>ZAH_PERFIL_COLABORADOR</VEPNAME>
      <VERSION>A</VERSION>
      <TYPENAME>PAD_CNAME</TYPENAME>
      <KIND>DTEL</KIND>
      <BUILD_IN_TYPE>CHAR</BUILD_IN_TYPE>
      <LENGTH>80</LENGTH>
      <ABAPTYPE>C</ABAPTYPE>
     </VEPELEMTYPE>
     <VEPELEMTYPE>
      <VEPNAME>ZAH_PERFIL_COLABORADOR</VEPNAME>
      <VERSION>A</VERSION>
      <TYPENAME>PAD_NACHN</TYPENAME>
      <KIND>DTEL</KIND>
      <BUILD_IN_TYPE>CHAR</BUILD_IN_TYPE>
      <LENGTH>40</LENGTH>
      <ABAPTYPE>C</ABAPTYPE>
     </VEPELEMTYPE>
     <VEPELEMTYPE>
      <VEPNAME>ZAH_PERFIL_COLABORADOR</VEPNAME>
      <VERSION>A</VERSION>
      <TYPENAME>PAD_ORT01</TYPENAME>
      <KIND>DTEL</KIND>
      <BUILD_IN_TYPE>CHAR</BUILD_IN_TYPE>
      <LENGTH>40</LENGTH>
      <ABAPTYPE>C</ABAPTYPE>
     </VEPELEMTYPE>
     <VEPELEMTYPE>
      <VEPNAME>ZAH_PERFIL_COLABORADOR</VEPNAME>
      <VERSION>A</VERSION>
      <TYPENAME>PAD_VORNA</TYPENAME>
      <KIND>DTEL</KIND>
      <BUILD_IN_TYPE>CHAR</BUILD_IN_TYPE>
      <LENGTH>40</LENGTH>
      <ABAPTYPE>C</ABAPTYPE>
     </VEPELEMTYPE>
     <VEPELEMTYPE>
      <VEPNAME>ZAH_PERFIL_COLABORADOR</VEPNAME>
      <VERSION>A</VERSION>
      <TYPENAME>PERNR_D</TYPENAME>
      <KIND>DTEL</KIND>
      <BUILD_IN_TYPE>NUMC</BUILD_IN_TYPE>
      <LENGTH>8</LENGTH>
      <ABAPTYPE>N</ABAPTYPE>
     </VEPELEMTYPE>
     <VEPELEMTYPE>
      <VEPNAME>ZAH_PERFIL_COLABORADOR</VEPNAME>
      <VERSION>A</VERSION>
      <TYPENAME>PERSNO</TYPENAME>
      <KIND>DTEL</KIND>
      <BUILD_IN_TYPE>NUMC</BUILD_IN_TYPE>
      <LENGTH>8</LENGTH>
      <ABAPTYPE>N</ABAPTYPE>
     </VEPELEMTYPE>
     <VEPELEMTYPE>
      <VEPNAME>ZAH_PERFIL_COLABORADOR</VEPNAME>
      <VERSION>A</VERSION>
      <TYPENAME>PLSTX</TYPENAME>
      <KIND>DTEL</KIND>
      <BUILD_IN_TYPE>CHAR</BUILD_IN_TYPE>
      <LENGTH>25</LENGTH>
      <ABAPTYPE>C</ABAPTYPE>
     </VEPELEMTYPE>
     <VEPELEMTYPE>
      <VEPNAME>ZAH_PERFIL_COLABORADOR</VEPNAME>
      <VERSION>A</VERSION>
      <TYPENAME>PSG_IDNUM</TYPENAME>
      <KIND>DTEL</KIND>
      <BUILD_IN_TYPE>CHAR</BUILD_IN_TYPE>
      <LENGTH>30</LENGTH>
      <ABAPTYPE>C</ABAPTYPE>
     </VEPELEMTYPE>
     <VEPELEMTYPE>
      <VEPNAME>ZAH_PERFIL_COLABORADOR</VEPNAME>
      <VERSION>A</VERSION>
      <TYPENAME>PSTLZ_HR</TYPENAME>
      <KIND>DTEL</KIND>
      <BUILD_IN_TYPE>CHAR</BUILD_IN_TYPE>
      <LENGTH>10</LENGTH>
      <ABAPTYPE>C</ABAPTYPE>
     </VEPELEMTYPE>
     <VEPELEMTYPE>
      <VEPNAME>ZAH_PERFIL_COLABORADOR</VEPNAME>
      <VERSION>A</VERSION>
      <TYPENAME>STLTX</TYPENAME>
      <KIND>DTEL</KIND>
      <BUILD_IN_TYPE>CHAR</BUILD_IN_TYPE>
      <LENGTH>25</LENGTH>
      <ABAPTYPE>C</ABAPTYPE>
     </VEPELEMTYPE>
     <VEPELEMTYPE>
      <VEPNAME>ZAH_PERFIL_COLABORADOR</VEPNAME>
      <VERSION>A</VERSION>
      <TYPENAME>ZAMTHRTELE</TYPENAME>
      <KIND>DTEL</KIND>
      <BUILD_IN_TYPE>CHAR</BUILD_IN_TYPE>
      <LENGTH>15</LENGTH>
      <ABAPTYPE>C</ABAPTYPE>
     </VEPELEMTYPE>
    </PVEPELEMTYPE>
    <PVEPTABLETYPE>
     <VEPTABLETYPE>
      <VEPNAME>ZAH_PERFIL_COLABORADOR</VEPNAME>
      <VERSION>A</VERSION>
      <TYPENAME>ZAH_TT_NUM_EMP</TYPENAME>
      <TYPEREF>ZAH_S_NUM_EMP</TYPEREF>
     </VEPTABLETYPE>
     <VEPTABLETYPE>
      <VEPNAME>ZAH_PERFIL_COLABORADOR</VEPNAME>
      <VERSION>A</VERSION>
      <TYPENAME>ZAH_TT_USER_PROFILE</TYPENAME>
      <TYPEREF>ZAH_S_USER_PROFILE</TYPEREF>
     </VEPTABLETYPE>
     <VEPTABLETYPE>
      <VEPNAME>ZAH_PERFIL_COLABORADOR</VEPNAME>
      <VERSION>A</VERSION>
      <TYPENAME>ZahTtNumEmp</TYPENAME>
      <TYPEREF>ZahSNumEmp</TYPEREF>
     </VEPTABLETYPE>
     <VEPTABLETYPE>
      <VEPNAME>ZAH_PERFIL_COLABORADOR</VEPNAME>
      <VERSION>A</VERSION>
      <TYPENAME>ZahTtUserProfile</TYPENAME>
      <TYPEREF>ZahSUserProfile</TYPEREF>
     </VEPTABLETYPE>
    </PVEPTABLETYPE>
    <PVEPSTRUTYPE>
     <VEPSTRUTYPE>
      <VEPNAME>ZAH_PERFIL_COLABORADOR</VEPNAME>
      <VERSION>A</VERSION>
      <TYPENAME>ZAH_S_NUM_EMP</TYPENAME>
      <FIELDPOS>1</FIELDPOS>
      <FIELDNAME>NUM_EMP</FIELDNAME>
      <TYPEREF>PERNR_D</TYPEREF>
     </VEPSTRUTYPE>
     <VEPSTRUTYPE>
      <VEPNAME>ZAH_PERFIL_COLABORADOR</VEPNAME>
      <VERSION>A</VERSION>
      <TYPENAME>ZAH_S_USER_PROFILE</TYPENAME>
      <FIELDPOS>1</FIELDPOS>
      <FIELDNAME>NUM_COLABORADOR</FIELDNAME>
      <TYPEREF>PERSNO</TYPEREF>
     </VEPSTRUTYPE>
     <VEPSTRUTYPE>
      <VEPNAME>ZAH_PERFIL_COLABORADOR</VEPNAME>
      <VERSION>A</VERSION>
      <TYPENAME>ZAH_S_USER_PROFILE</TYPENAME>
      <FIELDPOS>2</FIELDPOS>
      <FIELDNAME>POSICAO</FIELDNAME>
      <TYPEREF>PLSTX</TYPEREF>
     </VEPSTRUTYPE>
     <VEPSTRUTYPE>
      <VEPNAME>ZAH_PERFIL_COLABORADOR</VEPNAME>
      <VERSION>A</VERSION>
      <TYPENAME>ZAH_S_USER_PROFILE</TYPENAME>
      <FIELDPOS>3</FIELDPOS>
      <FIELDNAME>CARGO</FIELDNAME>
      <TYPEREF>STLTX</TYPEREF>
     </VEPSTRUTYPE>
     <VEPSTRUTYPE>
      <VEPNAME>ZAH_PERFIL_COLABORADOR</VEPNAME>
      <VERSION>A</VERSION>
      <TYPENAME>ZAH_S_USER_PROFILE</TYPENAME>
      <FIELDPOS>4</FIELDPOS>
      <FIELDNAME>ID_GERENTE</FIELDNAME>
      <TYPEREF>CHAR8</TYPEREF>
     </VEPSTRUTYPE>
     <VEPSTRUTYPE>
      <VEPNAME>ZAH_PERFIL_COLABORADOR</VEPNAME>
      <VERSION>A</VERSION>
      <TYPENAME>ZAH_S_USER_PROFILE</TYPENAME>
      <FIELDPOS>5</FIELDPOS>
      <FIELDNAME>ID_ORGANIZACIONAL</FIELDNAME>
      <TYPEREF>ORGEH</TYPEREF>
     </VEPSTRUTYPE>
     <VEPSTRUTYPE>
      <VEPNAME>ZAH_PERFIL_COLABORADOR</VEPNAME>
      <VERSION>A</VERSION>
      <TYPENAME>ZAH_S_USER_PROFILE</TYPENAME>
      <FIELDPOS>6</FIELDPOS>
      <FIELDNAME>NOME_COMPLETO</FIELDNAME>
      <TYPEREF>PAD_CNAME</TYPEREF>
     </VEPSTRUTYPE>
     <VEPSTRUTYPE>
      <VEPNAME>ZAH_PERFIL_COLABORADOR</VEPNAME>
      <VERSION>A</VERSION>
      <TYPENAME>ZAH_S_USER_PROFILE</TYPENAME>
      <FIELDPOS>7</FIELDPOS>
      <FIELDNAME>PRIMEIRO_NOME</FIELDNAME>
      <TYPEREF>PAD_VORNA</TYPEREF>
     </VEPSTRUTYPE>
     <VEPSTRUTYPE>
      <VEPNAME>ZAH_PERFIL_COLABORADOR</VEPNAME>
      <VERSION>A</VERSION>
      <TYPENAME>ZAH_S_USER_PROFILE</TYPENAME>
      <FIELDPOS>8</FIELDPOS>
      <FIELDNAME>ULTIMO_NOME</FIELDNAME>
      <TYPEREF>PAD_NACHN</TYPEREF>
     </VEPSTRUTYPE>
     <VEPSTRUTYPE>
      <VEPNAME>ZAH_PERFIL_COLABORADOR</VEPNAME>
      <VERSION>A</VERSION>
      <TYPENAME>ZAH_S_USER_PROFILE</TYPENAME>
      <FIELDPOS>9</FIELDPOS>
      <FIELDNAME>GENERO</FIELDNAME>
      <TYPEREF>GESCH</TYPEREF>
     </VEPSTRUTYPE>
     <VEPSTRUTYPE>
      <VEPNAME>ZAH_PERFIL_COLABORADOR</VEPNAME>
      <VERSION>A</VERSION>
      <TYPENAME>ZAH_S_USER_PROFILE</TYPENAME>
      <FIELDPOS>10</FIELDPOS>
      <FIELDNAME>DATA_NASCIMENTO</FIELDNAME>
      <TYPEREF>GBDAT</TYPEREF>
     </VEPSTRUTYPE>
     <VEPSTRUTYPE>
      <VEPNAME>ZAH_PERFIL_COLABORADOR</VEPNAME>
      <VERSION>A</VERSION>
      <TYPENAME>ZAH_S_USER_PROFILE</TYPENAME>
      <FIELDPOS>11</FIELDPOS>
      <FIELDNAME>ESTADO_CIVIL</FIELDNAME>
      <TYPEREF>FATXT</TYPEREF>
     </VEPSTRUTYPE>
     <VEPSTRUTYPE>
      <VEPNAME>ZAH_PERFIL_COLABORADOR</VEPNAME>
      <VERSION>A</VERSION>
      <TYPENAME>ZAH_S_USER_PROFILE</TYPENAME>
      <FIELDPOS>12</FIELDPOS>
      <FIELDNAME>NACIONALIDADE</FIELDNAME>
      <TYPEREF>NATIO</TYPEREF>
     </VEPSTRUTYPE>
     <VEPSTRUTYPE>
      <VEPNAME>ZAH_PERFIL_COLABORADOR</VEPNAME>
      <VERSION>A</VERSION>
      <TYPENAME>ZAH_S_USER_PROFILE</TYPENAME>
      <FIELDPOS>13</FIELDPOS>
      <FIELDNAME>NR_TELEMOVEL</FIELDNAME>
      <TYPEREF>NUM9</TYPEREF>
     </VEPSTRUTYPE>
     <VEPSTRUTYPE>
      <VEPNAME>ZAH_PERFIL_COLABORADOR</VEPNAME>
      <VERSION>A</VERSION>
      <TYPENAME>ZAH_S_USER_PROFILE</TYPENAME>
      <FIELDPOS>14</FIELDPOS>
      <FIELDNAME>MORADA</FIELDNAME>
      <TYPEREF>CHAR75</TYPEREF>
     </VEPSTRUTYPE>
     <VEPSTRUTYPE>
      <VEPNAME>ZAH_PERFIL_COLABORADOR</VEPNAME>
      <VERSION>A</VERSION>
      <TYPENAME>ZAH_S_USER_PROFILE</TYPENAME>
      <FIELDPOS>15</FIELDPOS>
      <FIELDNAME>CIDADE</FIELDNAME>
      <TYPEREF>PAD_ORT01</TYPEREF>
     </VEPSTRUTYPE>
     <VEPSTRUTYPE>
      <VEPNAME>ZAH_PERFIL_COLABORADOR</VEPNAME>
      <VERSION>A</VERSION>
      <TYPENAME>ZAH_S_USER_PROFILE</TYPENAME>
      <FIELDPOS>16</FIELDPOS>
      <FIELDNAME>COD_POSTAL</FIELDNAME>
      <TYPEREF>PSTLZ_HR</TYPEREF>
     </VEPSTRUTYPE>
     <VEPSTRUTYPE>
      <VEPNAME>ZAH_PERFIL_COLABORADOR</VEPNAME>
      <VERSION>A</VERSION>
      <TYPENAME>ZAH_S_USER_PROFILE</TYPENAME>
      <FIELDPOS>17</FIELDPOS>
      <FIELDNAME>RECETOR</FIELDNAME>
      <TYPEREF>EMFTX</TYPEREF>
     </VEPSTRUTYPE>
     <VEPSTRUTYPE>
      <VEPNAME>ZAH_PERFIL_COLABORADOR</VEPNAME>
      <VERSION>A</VERSION>
      <TYPENAME>ZAH_S_USER_PROFILE</TYPENAME>
      <FIELDPOS>18</FIELDPOS>
      <FIELDNAME>BANCO</FIELDNAME>
      <TYPEREF>BANKA</TYPEREF>
     </VEPSTRUTYPE>
     <VEPSTRUTYPE>
      <VEPNAME>ZAH_PERFIL_COLABORADOR</VEPNAME>
      <VERSION>A</VERSION>
      <TYPENAME>ZAH_S_USER_PROFILE</TYPENAME>
      <FIELDPOS>19</FIELDPOS>
      <FIELDNAME>IBAN</FIELDNAME>
      <TYPEREF>IBAN</TYPEREF>
     </VEPSTRUTYPE>
     <VEPSTRUTYPE>
      <VEPNAME>ZAH_PERFIL_COLABORADOR</VEPNAME>
      <VERSION>A</VERSION>
      <TYPENAME>ZAH_S_USER_PROFILE</TYPENAME>
      <FIELDPOS>20</FIELDPOS>
      <FIELDNAME>NR_CONTA_BANCARIA</FIELDNAME>
      <TYPEREF>BANKN</TYPEREF>
     </VEPSTRUTYPE>
     <VEPSTRUTYPE>
      <VEPNAME>ZAH_PERFIL_COLABORADOR</VEPNAME>
      <VERSION>A</VERSION>
      <TYPENAME>ZAH_S_USER_PROFILE</TYPENAME>
      <FIELDPOS>21</FIELDPOS>
      <FIELDNAME>INICIO_CONTRATO</FIELDNAME>
      <TYPEREF>DATUM</TYPEREF>
     </VEPSTRUTYPE>
     <VEPSTRUTYPE>
      <VEPNAME>ZAH_PERFIL_COLABORADOR</VEPNAME>
      <VERSION>A</VERSION>
      <TYPENAME>ZAH_S_USER_PROFILE</TYPENAME>
      <FIELDPOS>22</FIELDPOS>
      <FIELDNAME>DURACAO_CONTRATO</FIELDNAME>
      <TYPEREF>CHAR5</TYPEREF>
     </VEPSTRUTYPE>
     <VEPSTRUTYPE>
      <VEPNAME>ZAH_PERFIL_COLABORADOR</VEPNAME>
      <VERSION>A</VERSION>
      <TYPENAME>ZAH_S_USER_PROFILE</TYPENAME>
      <FIELDPOS>23</FIELDPOS>
      <FIELDNAME>TIPO_CONTRATO</FIELDNAME>
      <TYPEREF>CTTXT</TYPEREF>
     </VEPSTRUTYPE>
     <VEPSTRUTYPE>
      <VEPNAME>ZAH_PERFIL_COLABORADOR</VEPNAME>
      <VERSION>A</VERSION>
      <TYPENAME>ZAH_S_USER_PROFILE</TYPENAME>
      <FIELDPOS>24</FIELDPOS>
      <FIELDNAME>NR_EMERGENCIA</FIELDNAME>
      <TYPEREF>ZAMTHRTELE</TYPEREF>
     </VEPSTRUTYPE>
     <VEPSTRUTYPE>
      <VEPNAME>ZAH_PERFIL_COLABORADOR</VEPNAME>
      <VERSION>A</VERSION>
      <TYPENAME>ZAH_S_USER_PROFILE</TYPENAME>
      <FIELDPOS>25</FIELDPOS>
      <FIELDNAME>EMAIL</FIELDNAME>
      <TYPEREF>COMM_ID_LONG</TYPEREF>
     </VEPSTRUTYPE>
     <VEPSTRUTYPE>
      <VEPNAME>ZAH_PERFIL_COLABORADOR</VEPNAME>
      <VERSION>A</VERSION>
      <TYPENAME>ZAH_S_USER_PROFILE</TYPENAME>
      <FIELDPOS>26</FIELDPOS>
      <FIELDNAME>CARTAO_CIDADAO</FIELDNAME>
      <TYPEREF>PSG_IDNUM</TYPEREF>
     </VEPSTRUTYPE>
     <VEPSTRUTYPE>
      <VEPNAME>ZAH_PERFIL_COLABORADOR</VEPNAME>
      <VERSION>A</VERSION>
      <TYPENAME>ZAH_S_USER_PROFILE</TYPENAME>
      <FIELDPOS>27</FIELDPOS>
      <FIELDNAME>BILHETE_IDENTIDADE</FIELDNAME>
      <TYPEREF>ICNUM</TYPEREF>
     </VEPSTRUTYPE>
     <VEPSTRUTYPE>
      <VEPNAME>ZAH_PERFIL_COLABORADOR</VEPNAME>
      <VERSION>A</VERSION>
      <TYPENAME>ZahSNumEmp</TYPENAME>
      <FIELDPOS>1</FIELDPOS>
      <FIELDNAME>NumEmp</FIELDNAME>
      <TYPEREF>PERNR_D</TYPEREF>
     </VEPSTRUTYPE>
     <VEPSTRUTYPE>
      <VEPNAME>ZAH_PERFIL_COLABORADOR</VEPNAME>
      <VERSION>A</VERSION>
      <TYPENAME>ZahSUserProfile</TYPENAME>
      <FIELDPOS>1</FIELDPOS>
      <FIELDNAME>NumColaborador</FIELDNAME>
      <TYPEREF>PERSNO</TYPEREF>
     </VEPSTRUTYPE>
     <VEPSTRUTYPE>
      <VEPNAME>ZAH_PERFIL_COLABORADOR</VEPNAME>
      <VERSION>A</VERSION>
      <TYPENAME>ZahSUserProfile</TYPENAME>
      <FIELDPOS>2</FIELDPOS>
      <FIELDNAME>Posicao</FIELDNAME>
      <TYPEREF>PLSTX</TYPEREF>
     </VEPSTRUTYPE>
     <VEPSTRUTYPE>
      <VEPNAME>ZAH_PERFIL_COLABORADOR</VEPNAME>
      <VERSION>A</VERSION>
      <TYPENAME>ZahSUserProfile</TYPENAME>
      <FIELDPOS>3</FIELDPOS>
      <FIELDNAME>Cargo</FIELDNAME>
      <TYPEREF>STLTX</TYPEREF>
     </VEPSTRUTYPE>
     <VEPSTRUTYPE>
      <VEPNAME>ZAH_PERFIL_COLABORADOR</VEPNAME>
      <VERSION>A</VERSION>
      <TYPENAME>ZahSUserProfile</TYPENAME>
      <FIELDPOS>4</FIELDPOS>
      <FIELDNAME>IdGerente</FIELDNAME>
      <TYPEREF>CHAR8</TYPEREF>
     </VEPSTRUTYPE>
     <VEPSTRUTYPE>
      <VEPNAME>ZAH_PERFIL_COLABORADOR</VEPNAME>
      <VERSION>A</VERSION>
      <TYPENAME>ZahSUserProfile</TYPENAME>
      <FIELDPOS>5</FIELDPOS>
      <FIELDNAME>IdOrganizacional</FIELDNAME>
      <TYPEREF>ORGEH</TYPEREF>
     </VEPSTRUTYPE>
     <VEPSTRUTYPE>
      <VEPNAME>ZAH_PERFIL_COLABORADOR</VEPNAME>
      <VERSION>A</VERSION>
      <TYPENAME>ZahSUserProfile</TYPENAME>
      <FIELDPOS>6</FIELDPOS>
      <FIELDNAME>NomeCompleto</FIELDNAME>
      <TYPEREF>PAD_CNAME</TYPEREF>
     </VEPSTRUTYPE>
     <VEPSTRUTYPE>
      <VEPNAME>ZAH_PERFIL_COLABORADOR</VEPNAME>
      <VERSION>A</VERSION>
      <TYPENAME>ZahSUserProfile</TYPENAME>
      <FIELDPOS>7</FIELDPOS>
      <FIELDNAME>PrimeiroNome</FIELDNAME>
      <TYPEREF>PAD_VORNA</TYPEREF>
     </VEPSTRUTYPE>
     <VEPSTRUTYPE>
      <VEPNAME>ZAH_PERFIL_COLABORADOR</VEPNAME>
      <VERSION>A</VERSION>
      <TYPENAME>ZahSUserProfile</TYPENAME>
      <FIELDPOS>8</FIELDPOS>
      <FIELDNAME>UltimoNome</FIELDNAME>
      <TYPEREF>PAD_NACHN</TYPEREF>
     </VEPSTRUTYPE>
     <VEPSTRUTYPE>
      <VEPNAME>ZAH_PERFIL_COLABORADOR</VEPNAME>
      <VERSION>A</VERSION>
      <TYPENAME>ZahSUserProfile</TYPENAME>
      <FIELDPOS>9</FIELDPOS>
      <FIELDNAME>Genero</FIELDNAME>
      <TYPEREF>GESCH</TYPEREF>
     </VEPSTRUTYPE>
     <VEPSTRUTYPE>
      <VEPNAME>ZAH_PERFIL_COLABORADOR</VEPNAME>
      <VERSION>A</VERSION>
      <TYPENAME>ZahSUserProfile</TYPENAME>
      <FIELDPOS>10</FIELDPOS>
      <FIELDNAME>DataNascimento</FIELDNAME>
      <TYPEREF>GBDAT</TYPEREF>
     </VEPSTRUTYPE>
     <VEPSTRUTYPE>
      <VEPNAME>ZAH_PERFIL_COLABORADOR</VEPNAME>
      <VERSION>A</VERSION>
      <TYPENAME>ZahSUserProfile</TYPENAME>
      <FIELDPOS>11</FIELDPOS>
      <FIELDNAME>EstadoCivil</FIELDNAME>
      <TYPEREF>FATXT</TYPEREF>
     </VEPSTRUTYPE>
     <VEPSTRUTYPE>
      <VEPNAME>ZAH_PERFIL_COLABORADOR</VEPNAME>
      <VERSION>A</VERSION>
      <TYPENAME>ZahSUserProfile</TYPENAME>
      <FIELDPOS>12</FIELDPOS>
      <FIELDNAME>Nacionalidade</FIELDNAME>
      <TYPEREF>NATIO</TYPEREF>
     </VEPSTRUTYPE>
     <VEPSTRUTYPE>
      <VEPNAME>ZAH_PERFIL_COLABORADOR</VEPNAME>
      <VERSION>A</VERSION>
      <TYPENAME>ZahSUserProfile</TYPENAME>
      <FIELDPOS>13</FIELDPOS>
      <FIELDNAME>NrTelemovel</FIELDNAME>
      <TYPEREF>NUM9</TYPEREF>
     </VEPSTRUTYPE>
     <VEPSTRUTYPE>
      <VEPNAME>ZAH_PERFIL_COLABORADOR</VEPNAME>
      <VERSION>A</VERSION>
      <TYPENAME>ZahSUserProfile</TYPENAME>
      <FIELDPOS>14</FIELDPOS>
      <FIELDNAME>Morada</FIELDNAME>
      <TYPEREF>CHAR75</TYPEREF>
     </VEPSTRUTYPE>
     <VEPSTRUTYPE>
      <VEPNAME>ZAH_PERFIL_COLABORADOR</VEPNAME>
      <VERSION>A</VERSION>
      <TYPENAME>ZahSUserProfile</TYPENAME>
      <FIELDPOS>15</FIELDPOS>
      <FIELDNAME>Cidade</FIELDNAME>
      <TYPEREF>PAD_ORT01</TYPEREF>
     </VEPSTRUTYPE>
     <VEPSTRUTYPE>
      <VEPNAME>ZAH_PERFIL_COLABORADOR</VEPNAME>
      <VERSION>A</VERSION>
      <TYPENAME>ZahSUserProfile</TYPENAME>
      <FIELDPOS>16</FIELDPOS>
      <FIELDNAME>CodPostal</FIELDNAME>
      <TYPEREF>PSTLZ_HR</TYPEREF>
     </VEPSTRUTYPE>
     <VEPSTRUTYPE>
      <VEPNAME>ZAH_PERFIL_COLABORADOR</VEPNAME>
      <VERSION>A</VERSION>
      <TYPENAME>ZahSUserProfile</TYPENAME>
      <FIELDPOS>17</FIELDPOS>
      <FIELDNAME>Recetor</FIELDNAME>
      <TYPEREF>EMFTX</TYPEREF>
     </VEPSTRUTYPE>
     <VEPSTRUTYPE>
      <VEPNAME>ZAH_PERFIL_COLABORADOR</VEPNAME>
      <VERSION>A</VERSION>
      <TYPENAME>ZahSUserProfile</TYPENAME>
      <FIELDPOS>18</FIELDPOS>
      <FIELDNAME>Banco</FIELDNAME>
      <TYPEREF>BANKA</TYPEREF>
     </VEPSTRUTYPE>
     <VEPSTRUTYPE>
      <VEPNAME>ZAH_PERFIL_COLABORADOR</VEPNAME>
      <VERSION>A</VERSION>
      <TYPENAME>ZahSUserProfile</TYPENAME>
      <FIELDPOS>19</FIELDPOS>
      <FIELDNAME>Iban</FIELDNAME>
      <TYPEREF>IBAN</TYPEREF>
     </VEPSTRUTYPE>
     <VEPSTRUTYPE>
      <VEPNAME>ZAH_PERFIL_COLABORADOR</VEPNAME>
      <VERSION>A</VERSION>
      <TYPENAME>ZahSUserProfile</TYPENAME>
      <FIELDPOS>20</FIELDPOS>
      <FIELDNAME>NrContaBancaria</FIELDNAME>
      <TYPEREF>BANKN</TYPEREF>
     </VEPSTRUTYPE>
     <VEPSTRUTYPE>
      <VEPNAME>ZAH_PERFIL_COLABORADOR</VEPNAME>
      <VERSION>A</VERSION>
      <TYPENAME>ZahSUserProfile</TYPENAME>
      <FIELDPOS>21</FIELDPOS>
      <FIELDNAME>InicioContrato</FIELDNAME>
      <TYPEREF>DATUM</TYPEREF>
     </VEPSTRUTYPE>
     <VEPSTRUTYPE>
      <VEPNAME>ZAH_PERFIL_COLABORADOR</VEPNAME>
      <VERSION>A</VERSION>
      <TYPENAME>ZahSUserProfile</TYPENAME>
      <FIELDPOS>22</FIELDPOS>
      <FIELDNAME>DuracaoContrato</FIELDNAME>
      <TYPEREF>CHAR5</TYPEREF>
     </VEPSTRUTYPE>
     <VEPSTRUTYPE>
      <VEPNAME>ZAH_PERFIL_COLABORADOR</VEPNAME>
      <VERSION>A</VERSION>
      <TYPENAME>ZahSUserProfile</TYPENAME>
      <FIELDPOS>23</FIELDPOS>
      <FIELDNAME>TipoContrato</FIELDNAME>
      <TYPEREF>CTTXT</TYPEREF>
     </VEPSTRUTYPE>
     <VEPSTRUTYPE>
      <VEPNAME>ZAH_PERFIL_COLABORADOR</VEPNAME>
      <VERSION>A</VERSION>
      <TYPENAME>ZahSUserProfile</TYPENAME>
      <FIELDPOS>24</FIELDPOS>
      <FIELDNAME>NrEmergencia</FIELDNAME>
      <TYPEREF>ZAMTHRTELE</TYPEREF>
     </VEPSTRUTYPE>
     <VEPSTRUTYPE>
      <VEPNAME>ZAH_PERFIL_COLABORADOR</VEPNAME>
      <VERSION>A</VERSION>
      <TYPENAME>ZahSUserProfile</TYPENAME>
      <FIELDPOS>25</FIELDPOS>
      <FIELDNAME>Email</FIELDNAME>
      <TYPEREF>COMM_ID_LONG</TYPEREF>
     </VEPSTRUTYPE>
     <VEPSTRUTYPE>
      <VEPNAME>ZAH_PERFIL_COLABORADOR</VEPNAME>
      <VERSION>A</VERSION>
      <TYPENAME>ZahSUserProfile</TYPENAME>
      <FIELDPOS>26</FIELDPOS>
      <FIELDNAME>CartaoCidadao</FIELDNAME>
      <TYPEREF>PSG_IDNUM</TYPEREF>
     </VEPSTRUTYPE>
     <VEPSTRUTYPE>
      <VEPNAME>ZAH_PERFIL_COLABORADOR</VEPNAME>
      <VERSION>A</VERSION>
      <TYPENAME>ZahSUserProfile</TYPENAME>
      <FIELDPOS>27</FIELDPOS>
      <FIELDNAME>BilheteIdentidade</FIELDNAME>
      <TYPEREF>ICNUM</TYPEREF>
     </VEPSTRUTYPE>
    </PVEPSTRUTYPE>
    <PVEPTYPESOAPEXT>
     <VEPTYPESOAPEXT>
      <VEPNAME>ZAH_PERFIL_COLABORADOR</VEPNAME>
      <VERSION>A</VERSION>
      <TYPENAME>BANKA</TYPENAME>
      <NAMESPACE>urn:sap-com:document:sap:rfc:functions</NAMESPACE>
     </VEPTYPESOAPEXT>
     <VEPTYPESOAPEXT>
      <VEPNAME>ZAH_PERFIL_COLABORADOR</VEPNAME>
      <VERSION>A</VERSION>
      <TYPENAME>BANKN</TYPENAME>
      <NAMESPACE>urn:sap-com:document:sap:rfc:functions</NAMESPACE>
     </VEPTYPESOAPEXT>
     <VEPTYPESOAPEXT>
      <VEPNAME>ZAH_PERFIL_COLABORADOR</VEPNAME>
      <VERSION>A</VERSION>
      <TYPENAME>CHAR4</TYPENAME>
      <NAMESPACE>urn:sap-com:document:sap:rfc:functions</NAMESPACE>
     </VEPTYPESOAPEXT>
     <VEPTYPESOAPEXT>
      <VEPNAME>ZAH_PERFIL_COLABORADOR</VEPNAME>
      <VERSION>A</VERSION>
      <TYPENAME>CHAR5</TYPENAME>
      <NAMESPACE>urn:sap-com:document:sap:rfc:functions</NAMESPACE>
     </VEPTYPESOAPEXT>
     <VEPTYPESOAPEXT>
      <VEPNAME>ZAH_PERFIL_COLABORADOR</VEPNAME>
      <VERSION>A</VERSION>
      <TYPENAME>CHAR75</TYPENAME>
      <NAMESPACE>urn:sap-com:document:sap:rfc:functions</NAMESPACE>
     </VEPTYPESOAPEXT>
     <VEPTYPESOAPEXT>
      <VEPNAME>ZAH_PERFIL_COLABORADOR</VEPNAME>
      <VERSION>A</VERSION>
      <TYPENAME>CHAR8</TYPENAME>
      <NAMESPACE>urn:sap-com:document:sap:soap:functions:mc-style</NAMESPACE>
     </VEPTYPESOAPEXT>
     <VEPTYPESOAPEXT>
      <VEPNAME>ZAH_PERFIL_COLABORADOR</VEPNAME>
      <VERSION>A</VERSION>
      <TYPENAME>COMM_ID_LONG</TYPENAME>
      <NAMESPACE>urn:sap-com:document:sap:rfc:functions</NAMESPACE>
     </VEPTYPESOAPEXT>
     <VEPTYPESOAPEXT>
      <VEPNAME>ZAH_PERFIL_COLABORADOR</VEPNAME>
      <VERSION>A</VERSION>
      <TYPENAME>CTTXT</TYPENAME>
      <NAMESPACE>urn:sap-com:document:sap:soap:functions:mc-style</NAMESPACE>
     </VEPTYPESOAPEXT>
     <VEPTYPESOAPEXT>
      <VEPNAME>ZAH_PERFIL_COLABORADOR</VEPNAME>
      <VERSION>A</VERSION>
      <TYPENAME>DATUM</TYPENAME>
      <NAMESPACE>urn:sap-com:document:sap:rfc:functions</NAMESPACE>
     </VEPTYPESOAPEXT>
     <VEPTYPESOAPEXT>
      <VEPNAME>ZAH_PERFIL_COLABORADOR</VEPNAME>
      <VERSION>A</VERSION>
      <TYPENAME>EMFTX</TYPENAME>
      <NAMESPACE>urn:sap-com:document:sap:rfc:functions</NAMESPACE>
     </VEPTYPESOAPEXT>
     <VEPTYPESOAPEXT>
      <VEPNAME>ZAH_PERFIL_COLABORADOR</VEPNAME>
      <VERSION>A</VERSION>
      <TYPENAME>FATXT</TYPENAME>
      <NAMESPACE>urn:sap-com:document:sap:rfc:functions</NAMESPACE>
     </VEPTYPESOAPEXT>
     <VEPTYPESOAPEXT>
      <VEPNAME>ZAH_PERFIL_COLABORADOR</VEPNAME>
      <VERSION>A</VERSION>
      <TYPENAME>GBDAT</TYPENAME>
      <NAMESPACE>urn:sap-com:document:sap:rfc:functions</NAMESPACE>
     </VEPTYPESOAPEXT>
     <VEPTYPESOAPEXT>
      <VEPNAME>ZAH_PERFIL_COLABORADOR</VEPNAME>
      <VERSION>A</VERSION>
      <TYPENAME>GESCH</TYPENAME>
      <NAMESPACE>urn:sap-com:document:sap:soap:functions:mc-style</NAMESPACE>
     </VEPTYPESOAPEXT>
     <VEPTYPESOAPEXT>
      <VEPNAME>ZAH_PERFIL_COLABORADOR</VEPNAME>
      <VERSION>A</VERSION>
      <TYPENAME>IBAN</TYPENAME>
      <NAMESPACE>urn:sap-com:document:sap:rfc:functions</NAMESPACE>
     </VEPTYPESOAPEXT>
     <VEPTYPESOAPEXT>
      <VEPNAME>ZAH_PERFIL_COLABORADOR</VEPNAME>
      <VERSION>A</VERSION>
      <TYPENAME>ICNUM</TYPENAME>
      <NAMESPACE>urn:sap-com:document:sap:rfc:functions</NAMESPACE>
     </VEPTYPESOAPEXT>
     <VEPTYPESOAPEXT>
      <VEPNAME>ZAH_PERFIL_COLABORADOR</VEPNAME>
      <VERSION>A</VERSION>
      <TYPENAME>NATIO</TYPENAME>
      <NAMESPACE>urn:sap-com:document:sap:rfc:functions</NAMESPACE>
     </VEPTYPESOAPEXT>
     <VEPTYPESOAPEXT>
      <VEPNAME>ZAH_PERFIL_COLABORADOR</VEPNAME>
      <VERSION>A</VERSION>
      <TYPENAME>NUM9</TYPENAME>
      <NAMESPACE>urn:sap-com:document:sap:rfc:functions</NAMESPACE>
     </VEPTYPESOAPEXT>
     <VEPTYPESOAPEXT>
      <VEPNAME>ZAH_PERFIL_COLABORADOR</VEPNAME>
      <VERSION>A</VERSION>
      <TYPENAME>ORGEH</TYPENAME>
      <NAMESPACE>urn:sap-com:document:sap:rfc:functions</NAMESPACE>
     </VEPTYPESOAPEXT>
     <VEPTYPESOAPEXT>
      <VEPNAME>ZAH_PERFIL_COLABORADOR</VEPNAME>
      <VERSION>A</VERSION>
      <TYPENAME>PAD_CNAME</TYPENAME>
      <NAMESPACE>urn:sap-com:document:sap:rfc:functions</NAMESPACE>
     </VEPTYPESOAPEXT>
     <VEPTYPESOAPEXT>
      <VEPNAME>ZAH_PERFIL_COLABORADOR</VEPNAME>
      <VERSION>A</VERSION>
      <TYPENAME>PAD_NACHN</TYPENAME>
      <NAMESPACE>urn:sap-com:document:sap:rfc:functions</NAMESPACE>
     </VEPTYPESOAPEXT>
     <VEPTYPESOAPEXT>
      <VEPNAME>ZAH_PERFIL_COLABORADOR</VEPNAME>
      <VERSION>A</VERSION>
      <TYPENAME>PAD_ORT01</TYPENAME>
      <NAMESPACE>urn:sap-com:document:sap:rfc:functions</NAMESPACE>
     </VEPTYPESOAPEXT>
     <VEPTYPESOAPEXT>
      <VEPNAME>ZAH_PERFIL_COLABORADOR</VEPNAME>
      <VERSION>A</VERSION>
      <TYPENAME>PAD_VORNA</TYPENAME>
      <NAMESPACE>urn:sap-com:document:sap:rfc:functions</NAMESPACE>
     </VEPTYPESOAPEXT>
     <VEPTYPESOAPEXT>
      <VEPNAME>ZAH_PERFIL_COLABORADOR</VEPNAME>
      <VERSION>A</VERSION>
      <TYPENAME>PERNR_D</TYPENAME>
      <NAMESPACE>urn:sap-com:document:sap:rfc:functions</NAMESPACE>
     </VEPTYPESOAPEXT>
     <VEPTYPESOAPEXT>
      <VEPNAME>ZAH_PERFIL_COLABORADOR</VEPNAME>
      <VERSION>A</VERSION>
      <TYPENAME>PERSNO</TYPENAME>
      <NAMESPACE>urn:sap-com:document:sap:rfc:functions</NAMESPACE>
     </VEPTYPESOAPEXT>
     <VEPTYPESOAPEXT>
      <VEPNAME>ZAH_PERFIL_COLABORADOR</VEPNAME>
      <VERSION>A</VERSION>
      <TYPENAME>PLSTX</TYPENAME>
      <NAMESPACE>urn:sap-com:document:sap:rfc:functions</NAMESPACE>
     </VEPTYPESOAPEXT>
     <VEPTYPESOAPEXT>
      <VEPNAME>ZAH_PERFIL_COLABORADOR</VEPNAME>
      <VERSION>A</VERSION>
      <TYPENAME>PSG_IDNUM</TYPENAME>
      <NAMESPACE>urn:sap-com:document:sap:rfc:functions</NAMESPACE>
     </VEPTYPESOAPEXT>
     <VEPTYPESOAPEXT>
      <VEPNAME>ZAH_PERFIL_COLABORADOR</VEPNAME>
      <VERSION>A</VERSION>
      <TYPENAME>PSTLZ_HR</TYPENAME>
      <NAMESPACE>urn:sap-com:document:sap:rfc:functions</NAMESPACE>
     </VEPTYPESOAPEXT>
     <VEPTYPESOAPEXT>
      <VEPNAME>ZAH_PERFIL_COLABORADOR</VEPNAME>
      <VERSION>A</VERSION>
      <TYPENAME>STLTX</TYPENAME>
      <NAMESPACE>urn:sap-com:document:sap:rfc:functions</NAMESPACE>
     </VEPTYPESOAPEXT>
     <VEPTYPESOAPEXT>
      <VEPNAME>ZAH_PERFIL_COLABORADOR</VEPNAME>
      <VERSION>A</VERSION>
      <TYPENAME>ZAH_S_NUM_EMP</TYPENAME>
      <NAMESPACE>urn:sap-com:document:sap:rfc:functions</NAMESPACE>
     </VEPTYPESOAPEXT>
     <VEPTYPESOAPEXT>
      <VEPNAME>ZAH_PERFIL_COLABORADOR</VEPNAME>
      <VERSION>A</VERSION>
      <TYPENAME>ZAH_S_USER_PROFILE</TYPENAME>
      <NAMESPACE>urn:sap-com:document:sap:rfc:functions</NAMESPACE>
     </VEPTYPESOAPEXT>
     <VEPTYPESOAPEXT>
      <VEPNAME>ZAH_PERFIL_COLABORADOR</VEPNAME>
      <VERSION>A</VERSION>
      <TYPENAME>ZAH_TT_NUM_EMP</TYPENAME>
      <NAMESPACE>urn:sap-com:document:sap:rfc:functions</NAMESPACE>
     </VEPTYPESOAPEXT>
     <VEPTYPESOAPEXT>
      <VEPNAME>ZAH_PERFIL_COLABORADOR</VEPNAME>
      <VERSION>A</VERSION>
      <TYPENAME>ZAH_TT_USER_PROFILE</TYPENAME>
      <NAMESPACE>urn:sap-com:document:sap:rfc:functions</NAMESPACE>
     </VEPTYPESOAPEXT>
     <VEPTYPESOAPEXT>
      <VEPNAME>ZAH_PERFIL_COLABORADOR</VEPNAME>
      <VERSION>A</VERSION>
      <TYPENAME>ZAMTHRTELE</TYPENAME>
      <NAMESPACE>urn:sap-com:document:sap:rfc:functions</NAMESPACE>
     </VEPTYPESOAPEXT>
     <VEPTYPESOAPEXT>
      <VEPNAME>ZAH_PERFIL_COLABORADOR</VEPNAME>
      <VERSION>A</VERSION>
      <TYPENAME>ZahSNumEmp</TYPENAME>
      <NAMESPACE>urn:sap-com:document:sap:soap:functions:mc-style</NAMESPACE>
     </VEPTYPESOAPEXT>
     <VEPTYPESOAPEXT>
      <VEPNAME>ZAH_PERFIL_COLABORADOR</VEPNAME>
      <VERSION>A</VERSION>
      <TYPENAME>ZahSUserProfile</TYPENAME>
      <NAMESPACE>urn:sap-com:document:sap:soap:functions:mc-style</NAMESPACE>
     </VEPTYPESOAPEXT>
     <VEPTYPESOAPEXT>
      <VEPNAME>ZAH_PERFIL_COLABORADOR</VEPNAME>
      <VERSION>A</VERSION>
      <TYPENAME>ZahTtNumEmp</TYPENAME>
      <NAMESPACE>urn:sap-com:document:sap:soap:functions:mc-style</NAMESPACE>
     </VEPTYPESOAPEXT>
     <VEPTYPESOAPEXT>
      <VEPNAME>ZAH_PERFIL_COLABORADOR</VEPNAME>
      <VERSION>A</VERSION>
      <TYPENAME>ZahTtUserProfile</TYPENAME>
      <NAMESPACE>urn:sap-com:document:sap:soap:functions:mc-style</NAMESPACE>
     </VEPTYPESOAPEXT>
    </PVEPTYPESOAPEXT>
    <PVEPTABTYPSOAP>
     <VEPTABTYPSOAP>
      <VEPNAME>ZAH_PERFIL_COLABORADOR</VEPNAME>
      <VERSION>A</VERSION>
      <TYPENAME>ZAH_TT_NUM_EMP</TYPENAME>
      <ITEMLABEL>item</ITEMLABEL>
     </VEPTABTYPSOAP>
     <VEPTABTYPSOAP>
      <VEPNAME>ZAH_PERFIL_COLABORADOR</VEPNAME>
      <VERSION>A</VERSION>
      <TYPENAME>ZAH_TT_USER_PROFILE</TYPENAME>
      <ITEMLABEL>item</ITEMLABEL>
     </VEPTABTYPSOAP>
    </PVEPTABTYPSOAP>
    <PVEPFUNCSOAPEXT>
     <VEPFUNCSOAPEXT>
      <VEPNAME>ZAH_PERFIL_COLABORADOR</VEPNAME>
      <VERSION>A</VERSION>
      <FUNCTION>ZAH_USER_PROFILE</FUNCTION>
      <NAMESPACE>urn:sap-com:document:sap:soap:functions:mc-style</NAMESPACE>
      <RESPONSENAME>ZahUserProfileResponse</RESPONSENAME>
      <REQUESTNAME>ZahUserProfile</REQUESTNAME>
     </VEPFUNCSOAPEXT>
    </PVEPFUNCSOAPEXT>
    <PVEPFIELDREF>
     <VEPFIELDREF>
      <VEPNAME>ZAH_PERFIL_COLABORADOR</VEPNAME>
      <VERSION>A</VERSION>
      <FUNCTION>ZAH_USER_PROFILE</FUNCTION>
      <VEPPARAM>EXP_USER_PROFILES</VEPPARAM>
      <VEPPARAMTYPE>O</VEPPARAMTYPE>
      <FIELDNAME>EXP_USER_PROFILES</FIELDNAME>
      <SUBSTRUCID>0000000001</SUBSTRUCID>
      <TYPE>T</TYPE>
      <TYPENAME>ZahTtUserProfile</TYPENAME>
     </VEPFIELDREF>
     <VEPFIELDREF>
      <VEPNAME>ZAH_PERFIL_COLABORADOR</VEPNAME>
      <VERSION>A</VERSION>
      <FUNCTION>ZAH_USER_PROFILE</FUNCTION>
      <VEPPARAM>EXP_USER_PROFILES</VEPPARAM>
      <VEPPARAMTYPE>O</VEPPARAMTYPE>
      <STRUCID>0000000001</STRUCID>
      <FIELDNAME>EXP_USER_PROFILES</FIELDNAME>
      <SUBSTRUCID>0000000002</SUBSTRUCID>
      <IS_INITIAL>X</IS_INITIAL>
      <TYPE>S</TYPE>
      <TYPENAME>ZahSUserProfile</TYPENAME>
     </VEPFIELDREF>
     <VEPFIELDREF>
      <VEPNAME>ZAH_PERFIL_COLABORADOR</VEPNAME>
      <VERSION>A</VERSION>
      <FUNCTION>ZAH_USER_PROFILE</FUNCTION>
      <VEPPARAM>EXP_USER_PROFILES</VEPPARAM>
      <VEPPARAMTYPE>O</VEPPARAMTYPE>
      <STRUCID>0000000002</STRUCID>
      <FIELDNAME>Banco</FIELDNAME>
      <SUBSTRUCID>0000000012</SUBSTRUCID>
      <IS_INITIAL>X</IS_INITIAL>
      <TYPE>E</TYPE>
      <TYPENAME>BANKA</TYPENAME>
     </VEPFIELDREF>
     <VEPFIELDREF>
      <VEPNAME>ZAH_PERFIL_COLABORADOR</VEPNAME>
      <VERSION>A</VERSION>
      <FUNCTION>ZAH_USER_PROFILE</FUNCTION>
      <VEPPARAM>EXP_USER_PROFILES</VEPPARAM>
      <VEPPARAMTYPE>O</VEPPARAMTYPE>
      <STRUCID>0000000002</STRUCID>
      <FIELDNAME>BilheteIdentidade</FIELDNAME>
      <SUBSTRUCID>0000000022</SUBSTRUCID>
      <IS_INITIAL>X</IS_INITIAL>
      <TYPE>E</TYPE>
      <TYPENAME>ICNUM</TYPENAME>
     </VEPFIELDREF>
     <VEPFIELDREF>
      <VEPNAME>ZAH_PERFIL_COLABORADOR</VEPNAME>
      <VERSION>A</VERSION>
      <FUNCTION>ZAH_USER_PROFILE</FUNCTION>
      <VEPPARAM>EXP_USER_PROFILES</VEPPARAM>
      <VEPPARAMTYPE>O</VEPPARAMTYPE>
      <STRUCID>0000000002</STRUCID>
      <FIELDNAME>Cargo</FIELDNAME>
      <SUBSTRUCID>0000000023</SUBSTRUCID>
      <IS_INITIAL>X</IS_INITIAL>
      <TYPE>E</TYPE>
      <TYPENAME>STLTX</TYPENAME>
     </VEPFIELDREF>
     <VEPFIELDREF>
      <VEPNAME>ZAH_PERFIL_COLABORADOR</VEPNAME>
      <VERSION>A</VERSION>
      <FUNCTION>ZAH_USER_PROFILE</FUNCTION>
      <VEPPARAM>EXP_USER_PROFILES</VEPPARAM>
      <VEPPARAMTYPE>O</VEPPARAMTYPE>
      <STRUCID>0000000002</STRUCID>
      <FIELDNAME>CartaoCidadao</FIELDNAME>
      <SUBSTRUCID>0000000021</SUBSTRUCID>
      <IS_INITIAL>X</IS_INITIAL>
      <TYPE>E</TYPE>
      <TYPENAME>PSG_IDNUM</TYPENAME>
     </VEPFIELDREF>
     <VEPFIELDREF>
      <VEPNAME>ZAH_PERFIL_COLABORADOR</VEPNAME>
      <VERSION>A</VERSION>
      <FUNCTION>ZAH_USER_PROFILE</FUNCTION>
      <VEPPARAM>EXP_USER_PROFILES</VEPPARAM>
      <VEPPARAMTYPE>O</VEPPARAMTYPE>
      <STRUCID>0000000002</STRUCID>
      <FIELDNAME>Cidade</FIELDNAME>
      <SUBSTRUCID>0000000009</SUBSTRUCID>
      <IS_INITIAL>X</IS_INITIAL>
      <TYPE>E</TYPE>
      <TYPENAME>PAD_ORT01</TYPENAME>
     </VEPFIELDREF>
     <VEPFIELDREF>
      <VEPNAME>ZAH_PERFIL_COLABORADOR</VEPNAME>
      <VERSION>A</VERSION>
      <FUNCTION>ZAH_USER_PROFILE</FUNCTION>
      <VEPPARAM>EXP_USER_PROFILES</VEPPARAM>
      <VEPPARAMTYPE>O</VEPPARAMTYPE>
      <STRUCID>0000000002</STRUCID>
      <FIELDNAME>CodPostal</FIELDNAME>
      <SUBSTRUCID>0000000010</SUBSTRUCID>
      <IS_INITIAL>X</IS_INITIAL>
      <TYPE>E</TYPE>
      <TYPENAME>PSTLZ_HR</TYPENAME>
     </VEPFIELDREF>
     <VEPFIELDREF>
      <VEPNAME>ZAH_PERFIL_COLABORADOR</VEPNAME>
      <VERSION>A</VERSION>
      <FUNCTION>ZAH_USER_PROFILE</FUNCTION>
      <VEPPARAM>EXP_USER_PROFILES</VEPPARAM>
      <VEPPARAMTYPE>O</VEPPARAMTYPE>
      <STRUCID>0000000002</STRUCID>
      <FIELDNAME>DataNascimento</FIELDNAME>
      <SUBSTRUCID>0000000004</SUBSTRUCID>
      <IS_INITIAL>X</IS_INITIAL>
      <TYPE>E</TYPE>
      <TYPENAME>GBDAT</TYPENAME>
     </VEPFIELDREF>
     <VEPFIELDREF>
      <VEPNAME>ZAH_PERFIL_COLABORADOR</VEPNAME>
      <VERSION>A</VERSION>
      <FUNCTION>ZAH_USER_PROFILE</FUNCTION>
      <VEPPARAM>EXP_USER_PROFILES</VEPPARAM>
      <VEPPARAMTYPE>O</VEPPARAMTYPE>
      <STRUCID>0000000002</STRUCID>
      <FIELDNAME>DuracaoContrato</FIELDNAME>
      <SUBSTRUCID>0000000017</SUBSTRUCID>
      <IS_INITIAL>X</IS_INITIAL>
      <TYPE>E</TYPE>
      <TYPENAME>CHAR5</TYPENAME>
     </VEPFIELDREF>
     <VEPFIELDREF>
      <VEPNAME>ZAH_PERFIL_COLABORADOR</VEPNAME>
      <VERSION>A</VERSION>
      <FUNCTION>ZAH_USER_PROFILE</FUNCTION>
      <VEPPARAM>EXP_USER_PROFILES</VEPPARAM>
      <VEPPARAMTYPE>O</VEPPARAMTYPE>
      <STRUCID>0000000002</STRUCID>
      <FIELDNAME>Email</FIELDNAME>
      <SUBSTRUCID>0000000020</SUBSTRUCID>
      <IS_INITIAL>X</IS_INITIAL>
      <TYPE>E</TYPE>
      <TYPENAME>COMM_ID_LONG</TYPENAME>
     </VEPFIELDREF>
     <VEPFIELDREF>
      <VEPNAME>ZAH_PERFIL_COLABORADOR</VEPNAME>
      <VERSION>A</VERSION>
      <FUNCTION>ZAH_USER_PROFILE</FUNCTION>
      <VEPPARAM>EXP_USER_PROFILES</VEPPARAM>
      <VEPPARAMTYPE>O</VEPPARAMTYPE>
      <STRUCID>0000000002</STRUCID>
      <FIELDNAME>EstadoCivil</FIELDNAME>
      <SUBSTRUCID>0000000005</SUBSTRUCID>
      <IS_INITIAL>X</IS_INITIAL>
      <TYPE>E</TYPE>
      <TYPENAME>FATXT</TYPENAME>
     </VEPFIELDREF>
     <VEPFIELDREF>
      <VEPNAME>ZAH_PERFIL_COLABORADOR</VEPNAME>
      <VERSION>A</VERSION>
      <FUNCTION>ZAH_USER_PROFILE</FUNCTION>
      <VEPPARAM>EXP_USER_PROFILES</VEPPARAM>
      <VEPPARAMTYPE>O</VEPPARAMTYPE>
      <STRUCID>0000000002</STRUCID>
      <FIELDNAME>Genero</FIELDNAME>
      <SUBSTRUCID>0000000029</SUBSTRUCID>
      <IS_INITIAL>X</IS_INITIAL>
      <TYPE>E</TYPE>
      <TYPENAME>GESCH</TYPENAME>
     </VEPFIELDREF>
     <VEPFIELDREF>
      <VEPNAME>ZAH_PERFIL_COLABORADOR</VEPNAME>
      <VERSION>A</VERSION>
      <FUNCTION>ZAH_USER_PROFILE</FUNCTION>
      <VEPPARAM>EXP_USER_PROFILES</VEPPARAM>
      <VEPPARAMTYPE>O</VEPPARAMTYPE>
      <STRUCID>0000000002</STRUCID>
      <FIELDNAME>Iban</FIELDNAME>
      <SUBSTRUCID>0000000013</SUBSTRUCID>
      <IS_INITIAL>X</IS_INITIAL>
      <TYPE>E</TYPE>
      <TYPENAME>IBAN</TYPENAME>
     </VEPFIELDREF>
     <VEPFIELDREF>
      <VEPNAME>ZAH_PERFIL_COLABORADOR</VEPNAME>
      <VERSION>A</VERSION>
      <FUNCTION>ZAH_USER_PROFILE</FUNCTION>
      <VEPPARAM>EXP_USER_PROFILES</VEPPARAM>
      <VEPPARAMTYPE>O</VEPPARAMTYPE>
      <STRUCID>0000000002</STRUCID>
      <FIELDNAME>IdGerente</FIELDNAME>
      <SUBSTRUCID>0000000024</SUBSTRUCID>
      <IS_INITIAL>X</IS_INITIAL>
      <TYPE>E</TYPE>
      <TYPENAME>CHAR8</TYPENAME>
     </VEPFIELDREF>
     <VEPFIELDREF>
      <VEPNAME>ZAH_PERFIL_COLABORADOR</VEPNAME>
      <VERSION>A</VERSION>
      <FUNCTION>ZAH_USER_PROFILE</FUNCTION>
      <VEPPARAM>EXP_USER_PROFILES</VEPPARAM>
      <VEPPARAMTYPE>O</VEPPARAMTYPE>
      <STRUCID>0000000002</STRUCID>
      <FIELDNAME>IdOrganizacional</FIELDNAME>
      <SUBSTRUCID>0000000025</SUBSTRUCID>
      <IS_INITIAL>X</IS_INITIAL>
      <TYPE>E</TYPE>
      <TYPENAME>ORGEH</TYPENAME>
     </VEPFIELDREF>
     <VEPFIELDREF>
      <VEPNAME>ZAH_PERFIL_COLABORADOR</VEPNAME>
      <VERSION>A</VERSION>
      <FUNCTION>ZAH_USER_PROFILE</FUNCTION>
      <VEPPARAM>EXP_USER_PROFILES</VEPPARAM>
      <VEPPARAMTYPE>O</VEPPARAMTYPE>
      <STRUCID>0000000002</STRUCID>
      <FIELDNAME>InicioContrato</FIELDNAME>
      <SUBSTRUCID>0000000016</SUBSTRUCID>
      <IS_INITIAL>X</IS_INITIAL>
      <TYPE>E</TYPE>
      <TYPENAME>DATUM</TYPENAME>
     </VEPFIELDREF>
     <VEPFIELDREF>
      <VEPNAME>ZAH_PERFIL_COLABORADOR</VEPNAME>
      <VERSION>A</VERSION>
      <FUNCTION>ZAH_USER_PROFILE</FUNCTION>
      <VEPPARAM>EXP_USER_PROFILES</VEPPARAM>
      <VEPPARAMTYPE>O</VEPPARAMTYPE>
      <STRUCID>0000000002</STRUCID>
      <FIELDNAME>Morada</FIELDNAME>
      <SUBSTRUCID>0000000008</SUBSTRUCID>
      <IS_INITIAL>X</IS_INITIAL>
      <TYPE>E</TYPE>
      <TYPENAME>CHAR75</TYPENAME>
     </VEPFIELDREF>
     <VEPFIELDREF>
      <VEPNAME>ZAH_PERFIL_COLABORADOR</VEPNAME>
      <VERSION>A</VERSION>
      <FUNCTION>ZAH_USER_PROFILE</FUNCTION>
      <VEPPARAM>EXP_USER_PROFILES</VEPPARAM>
      <VEPPARAMTYPE>O</VEPPARAMTYPE>
      <STRUCID>0000000002</STRUCID>
      <FIELDNAME>Nacionalidade</FIELDNAME>
      <SUBSTRUCID>0000000006</SUBSTRUCID>
      <IS_INITIAL>X</IS_INITIAL>
      <TYPE>E</TYPE>
      <TYPENAME>NATIO</TYPENAME>
     </VEPFIELDREF>
     <VEPFIELDREF>
      <VEPNAME>ZAH_PERFIL_COLABORADOR</VEPNAME>
      <VERSION>A</VERSION>
      <FUNCTION>ZAH_USER_PROFILE</FUNCTION>
      <VEPPARAM>EXP_USER_PROFILES</VEPPARAM>
      <VEPPARAMTYPE>O</VEPPARAMTYPE>
      <STRUCID>0000000002</STRUCID>
      <FIELDNAME>NomeCompleto</FIELDNAME>
      <SUBSTRUCID>0000000026</SUBSTRUCID>
      <IS_INITIAL>X</IS_INITIAL>
      <TYPE>E</TYPE>
      <TYPENAME>PAD_CNAME</TYPENAME>
     </VEPFIELDREF>
     <VEPFIELDREF>
      <VEPNAME>ZAH_PERFIL_COLABORADOR</VEPNAME>
      <VERSION>A</VERSION>
      <FUNCTION>ZAH_USER_PROFILE</FUNCTION>
      <VEPPARAM>EXP_USER_PROFILES</VEPPARAM>
      <VEPPARAMTYPE>O</VEPPARAMTYPE>
      <STRUCID>0000000002</STRUCID>
      <FIELDNAME>NrContaBancaria</FIELDNAME>
      <SUBSTRUCID>0000000015</SUBSTRUCID>
      <IS_INITIAL>X</IS_INITIAL>
      <TYPE>E</TYPE>
      <TYPENAME>BANKN</TYPENAME>
     </VEPFIELDREF>
     <VEPFIELDREF>
      <VEPNAME>ZAH_PERFIL_COLABORADOR</VEPNAME>
      <VERSION>A</VERSION>
      <FUNCTION>ZAH_USER_PROFILE</FUNCTION>
      <VEPPARAM>EXP_USER_PROFILES</VEPPARAM>
      <VEPPARAMTYPE>O</VEPPARAMTYPE>
      <STRUCID>0000000002</STRUCID>
      <FIELDNAME>NrEmergencia</FIELDNAME>
      <SUBSTRUCID>0000000019</SUBSTRUCID>
      <IS_INITIAL>X</IS_INITIAL>
      <TYPE>E</TYPE>
      <TYPENAME>ZAMTHRTELE</TYPENAME>
     </VEPFIELDREF>
     <VEPFIELDREF>
      <VEPNAME>ZAH_PERFIL_COLABORADOR</VEPNAME>
      <VERSION>A</VERSION>
      <FUNCTION>ZAH_USER_PROFILE</FUNCTION>
      <VEPPARAM>EXP_USER_PROFILES</VEPPARAM>
      <VEPPARAMTYPE>O</VEPPARAMTYPE>
      <STRUCID>0000000002</STRUCID>
      <FIELDNAME>NrTelemovel</FIELDNAME>
      <SUBSTRUCID>0000000007</SUBSTRUCID>
      <IS_INITIAL>X</IS_INITIAL>
      <TYPE>E</TYPE>
      <TYPENAME>NUM9</TYPENAME>
     </VEPFIELDREF>
     <VEPFIELDREF>
      <VEPNAME>ZAH_PERFIL_COLABORADOR</VEPNAME>
      <VERSION>A</VERSION>
      <FUNCTION>ZAH_USER_PROFILE</FUNCTION>
      <VEPPARAM>EXP_USER_PROFILES</VEPPARAM>
      <VEPPARAMTYPE>O</VEPPARAMTYPE>
      <STRUCID>0000000002</STRUCID>
      <FIELDNAME>NumColaborador</FIELDNAME>
      <SUBSTRUCID>0000000003</SUBSTRUCID>
      <IS_INITIAL>X</IS_INITIAL>
      <TYPE>E</TYPE>
      <TYPENAME>PERSNO</TYPENAME>
     </VEPFIELDREF>
     <VEPFIELDREF>
      <VEPNAME>ZAH_PERFIL_COLABORADOR</VEPNAME>
      <VERSION>A</VERSION>
      <FUNCTION>ZAH_USER_PROFILE</FUNCTION>
      <VEPPARAM>EXP_USER_PROFILES</VEPPARAM>
      <VEPPARAMTYPE>O</VEPPARAMTYPE>
      <STRUCID>0000000002</STRUCID>
      <FIELDNAME>Posicao</FIELDNAME>
      <SUBSTRUCID>0000000014</SUBSTRUCID>
      <IS_INITIAL>X</IS_INITIAL>
      <TYPE>E</TYPE>
      <TYPENAME>PLSTX</TYPENAME>
     </VEPFIELDREF>
     <VEPFIELDREF>
      <VEPNAME>ZAH_PERFIL_COLABORADOR</VEPNAME>
      <VERSION>A</VERSION>
      <FUNCTION>ZAH_USER_PROFILE</FUNCTION>
      <VEPPARAM>EXP_USER_PROFILES</VEPPARAM>
      <VEPPARAMTYPE>O</VEPPARAMTYPE>
      <STRUCID>0000000002</STRUCID>
      <FIELDNAME>PrimeiroNome</FIELDNAME>
      <SUBSTRUCID>0000000027</SUBSTRUCID>
      <IS_INITIAL>X</IS_INITIAL>
      <TYPE>E</TYPE>
      <TYPENAME>PAD_VORNA</TYPENAME>
     </VEPFIELDREF>
     <VEPFIELDREF>
      <VEPNAME>ZAH_PERFIL_COLABORADOR</VEPNAME>
      <VERSION>A</VERSION>
      <FUNCTION>ZAH_USER_PROFILE</FUNCTION>
      <VEPPARAM>EXP_USER_PROFILES</VEPPARAM>
      <VEPPARAMTYPE>O</VEPPARAMTYPE>
      <STRUCID>0000000002</STRUCID>
      <FIELDNAME>Recetor</FIELDNAME>
      <SUBSTRUCID>0000000011</SUBSTRUCID>
      <IS_INITIAL>X</IS_INITIAL>
      <TYPE>E</TYPE>
      <TYPENAME>EMFTX</TYPENAME>
     </VEPFIELDREF>
     <VEPFIELDREF>
      <VEPNAME>ZAH_PERFIL_COLABORADOR</VEPNAME>
      <VERSION>A</VERSION>
      <FUNCTION>ZAH_USER_PROFILE</FUNCTION>
      <VEPPARAM>EXP_USER_PROFILES</VEPPARAM>
      <VEPPARAMTYPE>O</VEPPARAMTYPE>
      <STRUCID>0000000002</STRUCID>
      <FIELDNAME>TipoContrato</FIELDNAME>
      <SUBSTRUCID>0000000018</SUBSTRUCID>
      <IS_INITIAL>X</IS_INITIAL>
      <TYPE>E</TYPE>
      <TYPENAME>CTTXT</TYPENAME>
     </VEPFIELDREF>
     <VEPFIELDREF>
      <VEPNAME>ZAH_PERFIL_COLABORADOR</VEPNAME>
      <VERSION>A</VERSION>
      <FUNCTION>ZAH_USER_PROFILE</FUNCTION>
      <VEPPARAM>EXP_USER_PROFILES</VEPPARAM>
      <VEPPARAMTYPE>O</VEPPARAMTYPE>
      <STRUCID>0000000002</STRUCID>
      <FIELDNAME>UltimoNome</FIELDNAME>
      <SUBSTRUCID>0000000028</SUBSTRUCID>
      <IS_INITIAL>X</IS_INITIAL>
      <TYPE>E</TYPE>
      <TYPENAME>PAD_NACHN</TYPENAME>
     </VEPFIELDREF>
     <VEPFIELDREF>
      <VEPNAME>ZAH_PERFIL_COLABORADOR</VEPNAME>
      <VERSION>A</VERSION>
      <FUNCTION>ZAH_USER_PROFILE</FUNCTION>
      <VEPPARAM>IT_NUM_COL</VEPPARAM>
      <VEPPARAMTYPE>I</VEPPARAMTYPE>
      <FIELDNAME>IT_NUM_COL</FIELDNAME>
      <SUBSTRUCID>0000000001</SUBSTRUCID>
      <TYPE>T</TYPE>
      <TYPENAME>ZahTtNumEmp</TYPENAME>
     </VEPFIELDREF>
     <VEPFIELDREF>
      <VEPNAME>ZAH_PERFIL_COLABORADOR</VEPNAME>
      <VERSION>A</VERSION>
      <FUNCTION>ZAH_USER_PROFILE</FUNCTION>
      <VEPPARAM>IT_NUM_COL</VEPPARAM>
      <VEPPARAMTYPE>I</VEPPARAMTYPE>
      <STRUCID>0000000001</STRUCID>
      <FIELDNAME>IT_NUM_COL</FIELDNAME>
      <SUBSTRUCID>0000000002</SUBSTRUCID>
      <IS_INITIAL>X</IS_INITIAL>
      <TYPE>S</TYPE>
      <TYPENAME>ZahSNumEmp</TYPENAME>
     </VEPFIELDREF>
     <VEPFIELDREF>
      <VEPNAME>ZAH_PERFIL_COLABORADOR</VEPNAME>
      <VERSION>A</VERSION>
      <FUNCTION>ZAH_USER_PROFILE</FUNCTION>
      <VEPPARAM>IT_NUM_COL</VEPPARAM>
      <VEPPARAMTYPE>I</VEPPARAMTYPE>
      <STRUCID>0000000002</STRUCID>
      <FIELDNAME>NumEmp</FIELDNAME>
      <SUBSTRUCID>0000000003</SUBSTRUCID>
      <IS_INITIAL>X</IS_INITIAL>
      <TYPE>E</TYPE>
      <TYPENAME>PERNR_D</TYPENAME>
     </VEPFIELDREF>
    </PVEPFIELDREF>
    <PVEPENDPOINT>
     <VEPENDPOINT>
      <RELID>VI</RELID>
      <VEPNAME>ZAH_PERFIL_COLABORADOR</VEPNAME>
      <VERSION>A</VERSION>
      <ENDPOINTTYPE>FUNC</ENDPOINTTYPE>
      <DATA_VERSION>1</DATA_VERSION>
      <DEF_START_PT>I</DEF_START_PT>
      <ENDPOINTNAME>ZAH_USER_PROFILE</ENDPOINTNAME>
      <CLUSTR>114</CLUSTR>
     </VEPENDPOINT>
    </PVEPENDPOINT>
    <PVEPVISOAPEXT>
     <VEPVISOAPEXT>
      <VEPNAME>ZAH_PERFIL_COLABORADOR</VEPNAME>
      <VERSION>A</VERSION>
      <NAMESPACE>urn:sap-com:document:sap:soap:functions:mc-style</NAMESPACE>
      <SOAP_APPL_URI>urn:sap-com:soap:runtime:application:rfc:710</SOAP_APPL_URI>
     </VEPVISOAPEXT>
    </PVEPVISOAPEXT>
    <PWSHEADER>
     <WSHEADER>
      <WSNAME>ZAH_PERFIL_COLABORADOR</WSNAME>
      <VERSION>A</VERSION>
      <WSNAMEEXT>ZAH_Perfil_colaborador</WSNAMEEXT>
      <PREFIX>/sap/bc/srt/rfc/sap/</PREFIX>
      <VINAME>ZAH_PERFIL_COLABORADOR</VINAME>
     </WSHEADER>
    </PWSHEADER>
    <PWSSOAPPROP>
     <WSSOAPPROP>
      <WSNAME>ZAH_PERFIL_COLABORADOR</WSNAME>
      <VERSION>A</VERSION>
      <FEATURE>http://www.sap.com/NW05/soap/features/blocking/</FEATURE>
      <SOAPAPP>FUNC</SOAPAPP>
      <FUNCREF>ZahUserProfile</FUNCREF>
      <PROPNUM>0001</PROPNUM>
      <PROPNAME>enableBlocking</PROPNAME>
      <VALUE>true</VALUE>
      <PROFILE_URI>PRF_DT_OP_COM_SYNC</PROFILE_URI>
     </WSSOAPPROP>
     <WSSOAPPROP>
      <WSNAME>ZAH_PERFIL_COLABORADOR</WSNAME>
      <VERSION>A</VERSION>
      <FEATURE>http://www.sap.com/NW05/soap/features/commit/</FEATURE>
      <SOAPAPP>FUNC</SOAPAPP>
      <FUNCREF>ZahUserProfile</FUNCREF>
      <PROPNUM>0001</PROPNUM>
      <PROPNAME>enableCommit</PROPNAME>
      <VALUE>false</VALUE>
      <PROFILE_URI>PRF_DT_OP_COM_SYNC</PROFILE_URI>
     </WSSOAPPROP>
     <WSSOAPPROP>
      <WSNAME>ZAH_PERFIL_COLABORADOR</WSNAME>
      <VERSION>A</VERSION>
      <FEATURE>http://www.sap.com/NW05/soap/features/transaction/</FEATURE>
      <SOAPAPP>FUNC</SOAPAPP>
      <FUNCREF>ZahUserProfile</FUNCREF>
      <PROPNUM>0001</PROPNUM>
      <PROPNAME>required</PROPNAME>
      <VALUE>no</VALUE>
      <PROFILE_URI>PRF_DT_OP_COM_SYNC</PROFILE_URI>
     </WSSOAPPROP>
     <WSSOAPPROP>
      <WSNAME>ZAH_PERFIL_COLABORADOR</WSNAME>
      <VERSION>A</VERSION>
      <FEATURE>http://www.sap.com/NW05/soap/features/wsrm/</FEATURE>
      <SOAPAPP>FUNC</SOAPAPP>
      <FUNCREF>ZahUserProfile</FUNCREF>
      <PROPNUM>0001</PROPNUM>
      <PROPNAME>enableWSRM</PROPNAME>
      <VALUE>false</VALUE>
      <PROFILE_URI>PRF_DT_OP_COM_SYNC</PROFILE_URI>
     </WSSOAPPROP>
     <WSSOAPPROP>
      <WSNAME>ZAH_PERFIL_COLABORADOR</WSNAME>
      <VERSION>A</VERSION>
      <FEATURE>http://www.sap.com/esi/NW05/rif/</FEATURE>
      <SOAPAPP>FUNC</SOAPAPP>
      <FUNCREF>ZahUserProfile</FUNCREF>
      <PROPNUM>0001</PROPNUM>
      <PROPNAME>mep</PROPNAME>
      <VALUE>RequestResponse</VALUE>
      <PROFILE_URI>PRF_DT_OP_COM_SYNC</PROFILE_URI>
     </WSSOAPPROP>
     <WSSOAPPROP>
      <WSNAME>ZAH_PERFIL_COLABORADOR</WSNAME>
      <VERSION>A</VERSION>
      <FEATURE>http://www.sap.com/webas/630/soap/features/authentication/</FEATURE>
      <SOAPAPP>FUNC</SOAPAPP>
      <PROPNUM>0001</PROPNUM>
      <PROPNAME>AuthenticationLevel</PROPNAME>
      <VALUE>None</VALUE>
      <PROFILE_URI>PRF_DT_IF_SEC_NO</PROFILE_URI>
     </WSSOAPPROP>
     <WSSOAPPROP>
      <WSNAME>ZAH_PERFIL_COLABORADOR</WSNAME>
      <VERSION>A</VERSION>
      <FEATURE>http://www.sap.com/webas/630/soap/features/session/</FEATURE>
      <SOAPAPP>FUNC</SOAPAPP>
      <PROPNUM>0001</PROPNUM>
      <PROPNAME>enableSession</PROPNAME>
      <VALUE>false</VALUE>
      <PROFILE_URI>PRF_DT_IF_COM_STATELESS</PROFILE_URI>
     </WSSOAPPROP>
     <WSSOAPPROP>
      <WSNAME>ZAH_PERFIL_COLABORADOR</WSNAME>
      <VERSION>A</VERSION>
      <FEATURE>http://www.sap.com/webas/630/soap/features/transportguarantee/</FEATURE>
      <SOAPAPP>FUNC</SOAPAPP>
      <PROPNUM>0001</PROPNUM>
      <PROPNAME>Level</PROPNAME>
      <VALUE>None</VALUE>
      <PROFILE_URI>PRF_DT_IF_SEC_NO</PROFILE_URI>
     </WSSOAPPROP>
     <WSSOAPPROP>
      <WSNAME>ZAH_PERFIL_COLABORADOR</WSNAME>
      <VERSION>A</VERSION>
      <FEATURE>http://www.sap.com/webas/640/soap/features/messageId/</FEATURE>
      <SOAPAPP>FUNC</SOAPAPP>
      <PROPNUM>0001</PROPNUM>
      <PROPNAME>enableMessageId</PROPNAME>
      <VALUE>true</VALUE>
      <PROFILE_URI>PRF_DT_IF_COM_STATELESS</PROFILE_URI>
     </WSSOAPPROP>
    </PWSSOAPPROP>
   </WEBI>
   <SOTR>
    <item>
     <HEADER>
      <CONCEPT>000C298C37EF1EDD9AFB210DF44BA0EE</CONCEPT>
      <CREA_LAN>P</CREA_LAN>
      <TRALA_TYPE>1</TRALA_TYPE>
      <OBJID_VEC>AAg=</OBJID_VEC>
     </HEADER>
     <ENTRIES>
      <SOTR_TEXT>
       <CONCEPT>000C298C37EF1EDD9AFB210DF44BA0EE</CONCEPT>
       <LANGU>P</LANGU>
       <LFD_NUM>0001</LFD_NUM>
       <FLAG_CNTXT>X</FLAG_CNTXT>
       <STATUS>R</STATUS>
       <LENGTH>051</LENGTH>
       <TEXT>Webservice - Perfil do Colaborador</TEXT>
      </SOTR_TEXT>
     </ENTRIES>
    </item>
   </SOTR>
   <SOTR_USE>
    <SOTR_USE>
     <PGMID>R3TR</PGMID>
     <OBJECT>WEBI</OBJECT>
     <OBJ_NAME>ZAH_PERFIL_COLABORADOR</OBJ_NAME>
     <CONCEPT>000C298C37EF1EDD9AFB210DF44BA0EE</CONCEPT>
     <LFD_NUM>0001</LFD_NUM>
    </SOTR_USE>
   </SOTR_USE>
  </asx:values>
 </asx:abap>
</abapGit>
